fb2_tools/fb2_edgetts.py
fb2_tools/fb2_inline.py
fb2_tools/fb2_inline_plaintext.py
fb2_tools/fb2_split.py
fb2_tools-0.1.2.dist-info/METADATA
fb2_tools-0.1.2.dist-info/WHEEL
fb2_tools-0.1.2.dist-info/entry_points.txt
fb2_tools-0.1.2.dist-info/RECORD
