Metadata-Version: 2.4
Name: fb2-tools
Version: 0.1.2
Summary: 
Author: dm1sh
Author-email: me@dmitriy.icu
Requires-Python: >=3.12
Classifier: Programming Language :: Python :: 3
Classifier: Programming Language :: Python :: 3.12
Classifier: Programming Language :: Python :: 3.13
Classifier: Programming Language :: Python :: 3.14
Requires-Dist: beautifulsoup4 (>=4.14.2,<5.0.0)
Requires-Dist: lxml (>=6.0.2,<7.0.0)
Requires-Dist: splinter[selenium] (>=0.21.0,<0.22.0)
